suitable/__init__.py
suitable/_module_types.py
suitable/_modules.py
suitable/api.py
suitable/callback.py
suitable/common.py
suitable/errors.py
suitable/inventory.py
suitable/mitogen.py
suitable/module_runner.py
suitable/py.typed
suitable/runner_results.py
suitable/types.py
suitable/utils.py
suitable-0.21.0.dist-info/licenses/LICENSE
suitable-0.21.0.dist-info/METADATA
suitable-0.21.0.dist-info/WHEEL
suitable-0.21.0.dist-info/top_level.txt
suitable-0.21.0.dist-info/RECORD
