Metadata-Version: 2.4
Name: suitable
Version: 0.21.0
Summary: Suitable is a thin wrapper around the Ansible API.
Home-page: http://github.com/seantis/suitable/
Author: Denis Krienbühl
Author-email: denis@href.ch
Maintainer: Seantis GmbH
Maintainer-email: info@seantis.ch
License: GPLv3
Classifier: Development Status :: 4 - Beta
Classifier: Intended Audience :: Developers
Classifier: License :: OSI Approved :: GNU General Public License v3 (GPLv3)
Classifier: Operating System :: OS Independent
Classifier: Programming Language :: Python
Classifier: Programming Language :: Python :: 3
Classifier: Programming Language :: Python :: 3.8
Classifier: Programming Language :: Python :: 3.9
Classifier: Programming Language :: Python :: 3.10
Classifier: Programming Language :: Python :: 3.11
Classifier: Programming Language :: Python :: 3.12
Classifier: Programming Language :: Python :: 3.13
Classifier: Programming Language :: Python :: Implementation :: CPython
Classifier: Topic :: Software Development :: Libraries :: Python Modules
Requires-Python: >=3.8
License-File: LICENSE
Requires-Dist: ansible>=6
Requires-Dist: ansible-core>=2.13
Requires-Dist: packaging
Provides-Extra: dev
Requires-Dist: bump-my-version; extra == "dev"
Requires-Dist: bandit[toml]; extra == "dev"
Requires-Dist: mypy; extra == "dev"
Requires-Dist: pre-commit; extra == "dev"
Requires-Dist: pre-commit-uv; extra == "dev"
Requires-Dist: ruff; extra == "dev"
Requires-Dist: tox; extra == "dev"
Requires-Dist: tox-uv; extra == "dev"
Requires-Dist: types-paramiko; extra == "dev"
Requires-Dist: types-pyyaml; extra == "dev"
Requires-Dist: uv; extra == "dev"
Provides-Extra: tests
Requires-Dist: mitogen>=0.3.7; extra == "tests"
Requires-Dist: paramiko; extra == "tests"
Requires-Dist: port-for; extra == "tests"
Requires-Dist: pytest; extra == "tests"
Requires-Dist: pytest-codecov[git]; extra == "tests"
Dynamic: license-file
